{
    "0": {
        "Buffer": 3.4322221279144287, 
        "Freezing": 0, 
        "QoE": 1.0, 
        "Representation": "1", 
        "Response": 1.5677108764648438, 
        "Server": "cache-01", 
        "TS": 1427430055
    }, 
    "1": {
        "Buffer": 6.383671045303345, 
        "Freezing": 0, 
        "QoE": 1.7515933508247599, 
        "Representation": "2", 
        "Response": 2.0484700202941895, 
        "Server": "cache-01", 
        "TS": 1427430057
    }, 
    "2": {
        "Buffer": 9.26730990409851, 
        "Freezing": 0, 
        "QoE": 1.7515933508247599, 
        "Representation": "2", 
        "Response": 2.1162850856781006, 
        "Server": "cache-01", 
        "TS": 1427430059
    }, 
    "3": {
        "Buffer": 12.720844984054565, 
        "Freezing": 0, 
        "QoE": 1.7515933508247599, 
        "Representation": "2", 
        "Response": 1.5463860034942627, 
        "Server": "cache-01", 
        "TS": 1427430061
    }, 
    "4": {
        "Buffer": 15.426505088806152, 
        "Freezing": 0, 
        "QoE": 1.7515933508247599, 
        "Representation": "2", 
        "Response": 2.2942628860473633, 
        "Server": "cache-01", 
        "TS": 1427430063
    }, 
    "5": {
        "Buffer": 17.069556951522827, 
        "Freezing": 0, 
        "QoE": 2.5031867016495197, 
        "Representation": "3", 
        "Response": 3.3568711280822754, 
        "Server": "cache-01", 
        "TS": 1427430066
    }, 
    "6": {
        "Buffer": 18.235799074172974, 
        "Freezing": 0, 
        "QoE": 2.9428406276733643, 
        "Representation": "4", 
        "Response": 3.833677053451538, 
        "Server": "cache-01", 
        "TS": 1427430070
    }, 
    "7": {
        "Buffer": 20.679776906967163, 
        "Freezing": 0, 
        "QoE": 2.9428406276733643, 
        "Representation": "4", 
        "Response": 2.5559401512145996, 
        "Server": "cache-01", 
        "TS": 1427430073
    }, 
    "8": {
        "Buffer": 23.64326310157776, 
        "Freezing": 0, 
        "QoE": 2.5031867016495197, 
        "Representation": "3", 
        "Response": 2.036435842514038, 
        "Server": "cache-01", 
        "TS": 1427430075
    }, 
    "9": {
        "Buffer": 25.52776002883911, 
        "Freezing": 0, 
        "QoE": 2.5031867016495197, 
        "Representation": "3", 
        "Response": 3.115424871444702, 
        "Server": "cache-01", 
        "TS": 1427430078
    }, 
    "10": {
        "Buffer": 22.927653074264526, 
        "Freezing": 0, 
        "QoE": 2.5031867016495197, 
        "Representation": "3", 
        "Response": 2.5949409008026123, 
        "Server": "cache-01", 
        "TS": 1427430085
    }, 
    "11": {
        "Buffer": 25.618025064468384, 
        "Freezing": 0, 
        "QoE": 2.9428406276733643, 
        "Representation": "4", 
        "Response": 2.3095479011535645, 
        "Server": "cache-01", 
        "TS": 1427430088
    }, 
    "12": {
        "Buffer": 23.291821002960205, 
        "Freezing": 0, 
        "QoE": 2.5031867016495197, 
        "Representation": "3", 
        "Response": 2.3210439682006836, 
        "Server": "cache-01", 
        "TS": 1427430095
    }, 
    "13": {
        "Buffer": 25.181243896484375, 
        "Freezing": 0, 
        "QoE": 2.5031867016495197, 
        "Representation": "3", 
        "Response": 3.073972225189209, 
        "Server": "cache-01", 
        "TS": 1427430098
    }, 
    "14": {
        "Buffer": 22.06996202468872, 
        "Freezing": 0, 
        "QoE": 2.9428406276733643, 
        "Representation": "4", 
        "Response": 3.1064939498901367, 
        "Server": "cache-01", 
        "TS": 1427430106
    }, 
    "15": {
        "Buffer": 22.253710985183716, 
        "Freezing": 0, 
        "QoE": 2.5031867016495197, 
        "Representation": "3", 
        "Response": 4.816172122955322, 
        "Server": "cache-01", 
        "TS": 1427430111
    }, 
    "16": {
        "Buffer": 24.636428117752075, 
        "Freezing": 0, 
        "QoE": 2.9428406276733643, 
        "Representation": "4", 
        "Response": 2.617196798324585, 
        "Server": "cache-01", 
        "TS": 1427430114
    }, 
    "17": {
        "Buffer": 27.818955898284912, 
        "Freezing": 0, 
        "QoE": 2.5031867016495197, 
        "Representation": "3", 
        "Response": 1.8173911571502686, 
        "Server": "cache-01", 
        "TS": 1427430116
    }, 
    "18": {
        "Buffer": 25.742414951324463, 
        "Freezing": 0, 
        "QoE": 2.5031867016495197, 
        "Representation": "3", 
        "Response": 2.0721540451049805, 
        "Server": "cache-01", 
        "TS": 1427430123
    }, 
    "19": {
        "Buffer": 22.800508975982666, 
        "Freezing": 0, 
        "QoE": 2.5031867016495197, 
        "Representation": "3", 
        "Response": 2.390916109085083, 
        "Server": "cache-01", 
        "TS": 1427430131
    }, 
    "20": {
        "Buffer": 25.14366102218628, 
        "Freezing": 0, 
        "QoE": 2.5031867016495197, 
        "Representation": "3", 
        "Response": 2.656770944595337, 
        "Server": "cache-01", 
        "TS": 1427430133
    }, 
    "21": {
        "Buffer": 22.590212106704712, 
        "Freezing": 0, 
        "QoE": 2.5031867016495197, 
        "Representation": "3", 
        "Response": 2.5483767986297607, 
        "Server": "cache-01", 
        "TS": 1427430141
    }, 
    "22": {
        "Buffer": 24.3819739818573, 
        "Freezing": 0, 
        "QoE": 2.5031867016495197, 
        "Representation": "3", 
        "Response": 3.208156108856201, 
        "Server": "cache-01", 
        "TS": 1427430144
    }, 
    "23": {
        "Buffer": 23.71280002593994, 
        "Freezing": 0, 
        "QoE": 2.9428406276733643, 
        "Representation": "4", 
        "Response": 5.669095993041992, 
        "Server": "cache-01", 
        "TS": 1427430150
    }, 
    "24": {
        "Buffer": 24.83967089653015, 
        "Freezing": 0, 
        "QoE": 2.9428406276733643, 
        "Representation": "4", 
        "Response": 3.8730521202087402, 
        "Server": "cache-01", 
        "TS": 1427430154
    }, 
    "25": {
        "Buffer": 26.38540291786194, 
        "Freezing": 0, 
        "QoE": 2.9428406276733643, 
        "Representation": "4", 
        "Response": 3.366986036300659, 
        "Server": "cache-01", 
        "TS": 1427430157
    }, 
    "26": {
        "Buffer": 22.721967935562134, 
        "Freezing": 0, 
        "QoE": 2.9428406276733643, 
        "Representation": "4", 
        "Response": 3.658545970916748, 
        "Server": "cache-01", 
        "TS": 1427430166
    }, 
    "27": {
        "Buffer": 24.877756118774414, 
        "Freezing": 0, 
        "QoE": 2.5031867016495197, 
        "Representation": "3", 
        "Response": 2.844132900238037, 
        "Server": "cache-01", 
        "TS": 1427430168
    }, 
    "28": {
        "Buffer": 26.493371963500977, 
        "Freezing": 0, 
        "QoE": 2.5031867016495197, 
        "Representation": "3", 
        "Response": 3.384305953979492, 
        "Server": "cache-01", 
        "TS": 1427430172
    }, 
    "29": {
        "Buffer": 23.568552017211914, 
        "Freezing": 0, 
        "QoE": 2.5031867016495197, 
        "Representation": "3", 
        "Response": 2.9198789596557617, 
        "Server": "cache-01", 
        "TS": 1427430180
    }, 
    "30": {
        "Buffer": 25.476706981658936, 
        "Freezing": 0, 
        "QoE": 2.5031867016495197, 
        "Representation": "3", 
        "Response": 3.091766119003296, 
        "Server": "cache-01", 
        "TS": 1427430183
    }, 
    "31": {
        "Buffer": 21.674959897994995, 
        "Freezing": 0, 
        "QoE": 2.5031867016495197, 
        "Representation": "3", 
        "Response": 2.5165250301361084, 
        "Server": "cache-01", 
        "TS": 1427430192
    }, 
    "32": {
        "Buffer": 23.20506501197815, 
        "Freezing": 0, 
        "QoE": 2.5031867016495197, 
        "Representation": "3", 
        "Response": 3.469818115234375, 
        "Server": "cache-01", 
        "TS": 1427430195
    }, 
    "33": {
        "Buffer": 24.232683897018433, 
        "Freezing": 0, 
        "QoE": 2.9428406276733643, 
        "Representation": "4", 
        "Response": 3.9723010063171387, 
        "Server": "cache-01", 
        "TS": 1427430199
    }, 
    "34": {
        "Buffer": 27.055102109909058, 
        "Freezing": 0, 
        "QoE": 2.9428406276733643, 
        "Representation": "4", 
        "Response": 2.177501916885376, 
        "Server": "cache-01", 
        "TS": 1427430201
    }, 
    "35": {
        "Buffer": 23.712759971618652, 
        "Freezing": 0, 
        "QoE": 2.5031867016495197, 
        "Representation": "3", 
        "Response": 3.3377270698547363, 
        "Server": "cache-01", 
        "TS": 1427430210
    }, 
    "36": {
        "Buffer": 23.6354079246521, 
        "Freezing": 0, 
        "QoE": 2.9428406276733643, 
        "Representation": "4", 
        "Response": 5.0772740840911865, 
        "Server": "cache-01", 
        "TS": 1427430215
    }, 
    "37": {
        "Buffer": 24.150805950164795, 
        "Freezing": 0, 
        "QoE": 2.9428406276733643, 
        "Representation": "4", 
        "Response": 4.451092958450317, 
        "Server": "cache-01", 
        "TS": 1427430219
    }, 
    "38": {
        "Buffer": 24.890607118606567, 
        "Freezing": 0, 
        "QoE": 2.9428406276733643, 
        "Representation": "4", 
        "Response": 4.260121822357178, 
        "Server": "cache-01", 
        "TS": 1427430223
    }, 
    "39": {
        "Buffer": 26.8962299823761, 
        "Freezing": 0, 
        "QoE": 2.5031867016495197, 
        "Representation": "3", 
        "Response": 2.994291067123413, 
        "Server": "cache-01", 
        "TS": 1427430226
    }, 
    "40": {
        "Buffer": 24.66548800468445, 
        "Freezing": 0, 
        "QoE": 2.5031867016495197, 
        "Representation": "3", 
        "Response": 2.2260940074920654, 
        "Server": "cache-01", 
        "TS": 1427430234
    }, 
    "41": {
        "Buffer": 26.500308990478516, 
        "Freezing": 0, 
        "QoE": 2.5031867016495197, 
        "Representation": "3", 
        "Response": 3.1650989055633545, 
        "Server": "cache-01", 
        "TS": 1427430237
    }, 
    "42": {
        "Buffer": 22.420372009277344, 
        "Freezing": 0, 
        "QoE": 2.5031867016495197, 
        "Representation": "3", 
        "Response": 4.074095010757446, 
        "Server": "cache-01", 
        "TS": 1427430246
    }, 
    "43": {
        "Buffer": 24.514678955078125, 
        "Freezing": 0, 
        "QoE": 2.9428406276733643, 
        "Representation": "4", 
        "Response": 2.813033103942871, 
        "Server": "cache-01", 
        "TS": 1427430249
    }, 
    "44": {
        "Buffer": 26.659471035003662, 
        "Freezing": 0, 
        "QoE": 2.9428406276733643, 
        "Representation": "4", 
        "Response": 2.8551268577575684, 
        "Server": "cache-01", 
        "TS": 1427430252
    }, 
    "45": {
        "Buffer": 23.528618097305298, 
        "Freezing": 0, 
        "QoE": 2.5031867016495197, 
        "Representation": "3", 
        "Response": 3.125854969024658, 
        "Server": "cache-01", 
        "TS": 1427430260
    }, 
    "46": {
        "Buffer": 25.676913022994995, 
        "Freezing": 0, 
        "QoE": 2.9428406276733643, 
        "Representation": "4", 
        "Response": 2.8516149520874023, 
        "Server": "cache-01", 
        "TS": 1427430263
    }, 
    "47": {
        "Buffer": 23.497462034225464, 
        "Freezing": 0, 
        "QoE": 2.5031867016495197, 
        "Representation": "3", 
        "Response": 2.174288034439087, 
        "Server": "cache-01", 
        "TS": 1427430270
    }, 
    "48": {
        "Buffer": 23.739378929138184, 
        "Freezing": 0, 
        "QoE": 2.5031867016495197, 
        "Representation": "3", 
        "Response": 4.7579991817474365, 
        "Server": "cache-01", 
        "TS": 1427430275
    }, 
    "49": {
        "Buffer": 23.978683948516846, 
        "Freezing": 0, 
        "QoE": 2.9428406276733643, 
        "Representation": "4", 
        "Response": 4.666630983352661, 
        "Server": "cache-01", 
        "TS": 1427430279
    }, 
    "50": {
        "Buffer": 24.44126605987549, 
        "Freezing": 0, 
        "QoE": 2.9428406276733643, 
        "Representation": "4", 
        "Response": 4.537338018417358, 
        "Server": "cache-01", 
        "TS": 1427430284
    }, 
    "51": {
        "Buffer": 26.620959043502808, 
        "Freezing": 0, 
        "QoE": 2.5031867016495197, 
        "Representation": "3", 
        "Response": 2.820227861404419, 
        "Server": "cache-01", 
        "TS": 1427430287
    }, 
    "52": {
        "Buffer": 23.27837610244751, 
        "Freezing": 0, 
        "QoE": 2.9428406276733643, 
        "Representation": "4", 
        "Response": 3.3374178409576416, 
        "Server": "cache-01", 
        "TS": 1427430295
    }, 
    "53": {
        "Buffer": 25.433243989944458, 
        "Freezing": 0, 
        "QoE": 2.9428406276733643, 
        "Representation": "4", 
        "Response": 2.84505295753479, 
        "Server": "cache-01", 
        "TS": 1427430298
    }, 
    "54": {
        "Buffer": 20.434120893478394, 
        "Freezing": 0, 
        "QoE": 2.9428406276733643, 
        "Representation": "4", 
        "Response": 4.9944422245025635, 
        "Server": "cache-01", 
        "TS": 1427430308
    }, 
    "55": {
        "Buffer": 19.957592010498047, 
        "Freezing": 0, 
        "QoE": 2.9428406276733643, 
        "Representation": "4", 
        "Response": 4.731687068939209, 
        "Server": "cache-01", 
        "TS": 1427430313
    }, 
    "56": {
        "Buffer": 21.85523295402527, 
        "Freezing": 0, 
        "QoE": 2.5031867016495197, 
        "Representation": "3", 
        "Response": 3.102281093597412, 
        "Server": "cache-01", 
        "TS": 1427430317
    }, 
    "57": {
        "Buffer": 24.956203937530518, 
        "Freezing": 0, 
        "QoE": 2.5031867016495197, 
        "Representation": "3", 
        "Response": 1.8989520072937012, 
        "Server": "cache-01", 
        "TS": 1427430318
    }, 
    "58": {
        "Buffer": 27.233803033828735, 
        "Freezing": 0, 
        "QoE": 2.5031867016495197, 
        "Representation": "3", 
        "Response": 2.722320079803467, 
        "Server": "cache-01", 
        "TS": 1427430321
    }, 
    "59": {
        "Buffer": 24.78292489051819, 
        "Freezing": 0, 
        "QoE": 2.5031867016495197, 
        "Representation": "3", 
        "Response": 2.446639060974121, 
        "Server": "cache-01", 
        "TS": 1427430329
    }, 
    "60": {
        "Buffer": 25.196115016937256, 
        "Freezing": 0, 
        "QoE": 2.5031867016495197, 
        "Representation": "3", 
        "Response": 4.586726903915405, 
        "Server": "cache-01", 
        "TS": 1427430333
    }, 
    "61": {
        "Buffer": 19.99789595603943, 
        "Freezing": 0, 
        "QoE": 2.9428406276733643, 
        "Representation": "4", 
        "Response": 4.690577983856201, 
        "Server": "cache-01", 
        "TS": 1427430343
    }, 
    "62": {
        "Buffer": 21.65003204345703, 
        "Freezing": 0, 
        "QoE": 2.5031867016495197, 
        "Representation": "3", 
        "Response": 3.3477840423583984, 
        "Server": "cache-01", 
        "TS": 1427430347
    }, 
    "63": {
        "Buffer": 22.921478033065796, 
        "Freezing": 0, 
        "QoE": 2.9428406276733643, 
        "Representation": "4", 
        "Response": 3.7284750938415527, 
        "Server": "cache-01", 
        "TS": 1427430350
    }, 
    "64": {
        "Buffer": 24.162463903427124, 
        "Freezing": 0, 
        "QoE": 2.9428406276733643, 
        "Representation": "4", 
        "Response": 3.7589340209960938, 
        "Server": "cache-01", 
        "TS": 1427430354
    }, 
    "65": {
        "Buffer": 25.117873907089233, 
        "Freezing": 0, 
        "QoE": 2.9428406276733643, 
        "Representation": "4", 
        "Response": 4.043495178222656, 
        "Server": "cache-01", 
        "TS": 1427430358
    }, 
    "66": {
        "Buffer": 21.24004292488098, 
        "Freezing": 0, 
        "QoE": 2.9428406276733643, 
        "Representation": "4", 
        "Response": 3.873509168624878, 
        "Server": "cache-01", 
        "TS": 1427430367
    }, 
    "67": {
        "Buffer": 23.47238802909851, 
        "Freezing": 0, 
        "QoE": 2.5031867016495197, 
        "Representation": "3", 
        "Response": 2.660240888595581, 
        "Server": "cache-01", 
        "TS": 1427430370
    }, 
    "68": {
        "Buffer": 25.449486017227173, 
        "Freezing": 0, 
        "QoE": 2.5031867016495197, 
        "Representation": "3", 
        "Response": 3.0228230953216553, 
        "Server": "cache-01", 
        "TS": 1427430373
    }, 
    "69": {
        "Buffer": 21.854636907577515, 
        "Freezing": 0, 
        "QoE": 2.5031867016495197, 
        "Representation": "3", 
        "Response": 3.589829206466675, 
        "Server": "cache-01", 
        "TS": 1427430382
    }, 
    "70": {
        "Buffer": 22.48309898376465, 
        "Freezing": 0, 
        "QoE": 2.9428406276733643, 
        "Representation": "4", 
        "Response": 4.371455907821655, 
        "Server": "cache-01", 
        "TS": 1427430386
    }, 
    "71": {
        "Buffer": 22.619858026504517, 
        "Freezing": 0, 
        "QoE": 2.9428406276733643, 
        "Representation": "4", 
        "Response": 4.863161087036133, 
        "Server": "cache-01", 
        "TS": 1427430391
    }, 
    "72": {
        "Buffer": 24.222731113433838, 
        "Freezing": 0, 
        "QoE": 2.9428406276733643, 
        "Representation": "4", 
        "Response": 3.397047996520996, 
        "Server": "cache-01", 
        "TS": 1427430394
    }, 
    "73": {
        "Buffer": 23.241440057754517, 
        "Freezing": 0, 
        "QoE": 2.9428406276733643, 
        "Representation": "4", 
        "Response": 5.899212837219238, 
        "Server": "cache-01", 
        "TS": 1427430400
    }, 
    "74": {
        "Buffer": 24.68445110321045, 
        "Freezing": 0, 
        "QoE": 2.5031867016495197, 
        "Representation": "3", 
        "Response": 3.5569097995758057, 
        "Server": "cache-01", 
        "TS": 1427430404
    }, 
    "75": {
        "Buffer": 26.9114511013031, 
        "Freezing": 0, 
        "QoE": 2.5031867016495197, 
        "Representation": "3", 
        "Response": 2.772920846939087, 
        "Server": "cache-01", 
        "TS": 1427430406
    }, 
    "76": {
        "Buffer": 25.09881591796875, 
        "Freezing": 0, 
        "QoE": 2.5031867016495197, 
        "Representation": "3", 
        "Response": 1.8077661991119385, 
        "Server": "cache-01", 
        "TS": 1427430413
    }, 
    "77": {
        "Buffer": 23.57043194770813, 
        "Freezing": 0, 
        "QoE": 2.5031867016495197, 
        "Representation": "3", 
        "Response": 1.524156093597412, 
        "Server": "cache-01", 
        "TS": 1427430420
    }, 
    "78": {
        "Buffer": 25.972863912582397, 
        "Freezing": 0, 
        "QoE": 2.5031867016495197, 
        "Representation": "3", 
        "Response": 2.59748911857605, 
        "Server": "cache-01", 
        "TS": 1427430422
    }, 
    "79": {
        "Buffer": 23.349785089492798, 
        "Freezing": 0, 
        "QoE": 2.5031867016495197, 
        "Representation": "3", 
        "Response": 2.33278489112854, 
        "Server": "cache-01", 
        "TS": 1427430430
    }, 
    "80": {
        "Buffer": 26.299143075942993, 
        "Freezing": 0, 
        "QoE": 2.5031867016495197, 
        "Representation": "3", 
        "Response": 2.050562858581543, 
        "Server": "cache-01", 
        "TS": 1427430432
    }, 
    "81": {
        "Buffer": 24.21734595298767, 
        "Freezing": 0, 
        "QoE": 2.5031867016495197, 
        "Representation": "3", 
        "Response": 2.0772171020507812, 
        "Server": "cache-01", 
        "TS": 1427430439
    }, 
    "82": {
        "Buffer": 26.370233058929443, 
        "Freezing": 0, 
        "QoE": 2.5031867016495197, 
        "Representation": "3", 
        "Response": 2.847033977508545, 
        "Server": "cache-01", 
        "TS": 1427430442
    }, 
    "83": {
        "Buffer": 22.971055030822754, 
        "Freezing": 0, 
        "QoE": 2.9428406276733643, 
        "Representation": "4", 
        "Response": 3.395458936691284, 
        "Server": "cache-01", 
        "TS": 1427430450
    }, 
    "84": {
        "Buffer": 19.689785957336426, 
        "Freezing": 0, 
        "QoE": 2.9428406276733643, 
        "Representation": "4", 
        "Response": 8.281191110610962, 
        "Server": "cache-01", 
        "TS": 1427430459
    }, 
    "85": {
        "Buffer": 20.42494511604309, 
        "Freezing": 0, 
        "QoE": 2.9428406276733643, 
        "Representation": "4", 
        "Response": 4.230174779891968, 
        "Server": "cache-01", 
        "TS": 1427430463
    }, 
    "86": {
        "Buffer": 18.583436965942383, 
        "Freezing": 0, 
        "QoE": 2.9428406276733643, 
        "Representation": "4", 
        "Response": 6.841421127319336, 
        "Server": "cache-01", 
        "TS": 1427430470
    }, 
    "87": {
        "Buffer": 20.646785974502563, 
        "Freezing": 0, 
        "QoE": 2.9428406276733643, 
        "Representation": "4", 
        "Response": 2.9365720748901367, 
        "Server": "cache-01", 
        "TS": 1427430473
    }, 
    "88": {
        "Buffer": 20.848073959350586, 
        "Freezing": 0, 
        "QoE": 2.9428406276733643, 
        "Representation": "4", 
        "Response": 4.797662973403931, 
        "Server": "cache-01", 
        "TS": 1427430478
    }, 
    "89": {
        "Buffer": 23.97573208808899, 
        "Freezing": 0, 
        "QoE": 2.9428406276733643, 
        "Representation": "4", 
        "Response": 1.872262954711914, 
        "Server": "cache-01", 
        "TS": 1427430479
    }, 
    "90": {
        "Buffer": 26.934925079345703, 
        "Freezing": 0, 
        "QoE": 2.5031867016495197, 
        "Representation": "3", 
        "Response": 2.0407159328460693, 
        "Server": "cache-01", 
        "TS": 1427430481
    }, 
    "91": {
        "Buffer": 24.21851110458374, 
        "Freezing": 0, 
        "QoE": 2.5031867016495197, 
        "Representation": "3", 
        "Response": 2.605958938598633, 
        "Server": "cache-01", 
        "TS": 1427430489
    }, 
    "92": {
        "Buffer": 26.418653964996338, 
        "Freezing": 0, 
        "QoE": 2.5031867016495197, 
        "Representation": "3", 
        "Response": 2.799778938293457, 
        "Server": "cache-01", 
        "TS": 1427430492
    }, 
    "93": {
        "Buffer": 22.663300037384033, 
        "Freezing": 0, 
        "QoE": 2.5031867016495197, 
        "Representation": "3", 
        "Response": 3.750185966491699, 
        "Server": "cache-01", 
        "TS": 1427430501
    }, 
    "94": {
        "Buffer": 25.446794986724854, 
        "Freezing": 0, 
        "QoE": 2.5031867016495197, 
        "Representation": "3", 
        "Response": 2.2164270877838135, 
        "Server": "cache-01", 
        "TS": 1427430503
    }, 
    "95": {
        "Buffer": 23.610299110412598, 
        "Freezing": 0, 
        "QoE": 2.5031867016495197, 
        "Representation": "3", 
        "Response": 1.831326961517334, 
        "Server": "cache-01", 
        "TS": 1427430510
    }, 
    "96": {
        "Buffer": 26.83641505241394, 
        "Freezing": 0, 
        "QoE": 2.5031867016495197, 
        "Representation": "3", 
        "Response": 1.7738070487976074, 
        "Server": "cache-01", 
        "TS": 1427430512
    }, 
    "97": {
        "Buffer": 24.90380096435547, 
        "Freezing": 0, 
        "QoE": 2.5031867016495197, 
        "Representation": "3", 
        "Response": 1.8187620639801025, 
        "Server": "cache-01", 
        "TS": 1427430518
    }, 
    "98": {
        "Buffer": 28.095003128051758, 
        "Freezing": 0, 
        "QoE": 2.5031867016495197, 
        "Representation": "3", 
        "Response": 1.8087217807769775, 
        "Server": "cache-01", 
        "TS": 1427430520
    }, 
    "99": {
        "Buffer": 26.0070641040802, 
        "Freezing": 0, 
        "QoE": 2.5031867016495197, 
        "Representation": "3", 
        "Response": 2.0834059715270996, 
        "Server": "cache-01", 
        "TS": 1427430527
    }, 
    "100": {
        "Buffer": 23.668433904647827, 
        "Freezing": 0, 
        "QoE": 2.5031867016495197, 
        "Representation": "3", 
        "Response": 2.333739995956421, 
        "Server": "cache-01", 
        "TS": 1427430535
    }, 
    "101": {
        "Buffer": 25.870455980300903, 
        "Freezing": 0, 
        "QoE": 2.5031867016495197, 
        "Representation": "3", 
        "Response": 2.797900915145874, 
        "Server": "cache-01", 
        "TS": 1427430538
    }, 
    "102": {
        "Buffer": 22.134593963623047, 
        "Freezing": 0, 
        "QoE": 2.9428406276733643, 
        "Representation": "4", 
        "Response": 3.7306900024414062, 
        "Server": "cache-01", 
        "TS": 1427430546
    }, 
    "103": {
        "Buffer": 23.13013792037964, 
        "Freezing": 0, 
        "QoE": 2.9428406276733643, 
        "Representation": "4", 
        "Response": 3.970668077468872, 
        "Server": "cache-01", 
        "TS": 1427430550
    }, 
    "104": {
        "Buffer": 24.115797996520996, 
        "Freezing": 0, 
        "QoE": 2.9428406276733643, 
        "Representation": "4", 
        "Response": 4.014261960983276, 
        "Server": "cache-01", 
        "TS": 1427430554
    }, 
    "105": {
        "Buffer": 25.399971961975098, 
        "Freezing": 0, 
        "QoE": 2.9428406276733643, 
        "Representation": "4", 
        "Response": 3.7157461643218994, 
        "Server": "cache-01", 
        "TS": 1427430558
    }, 
    "106": {
        "Buffer": 21.41066598892212, 
        "Freezing": 0, 
        "QoE": 2.9428406276733643, 
        "Representation": "4", 
        "Response": 3.9849190711975098, 
        "Server": "cache-01", 
        "TS": 1427430567
    }, 
    "107": {
        "Buffer": 20.439690113067627, 
        "Freezing": 0, 
        "QoE": 2.9428406276733643, 
        "Representation": "4", 
        "Response": 5.97089695930481, 
        "Server": "cache-01", 
        "TS": 1427430573
    }, 
    "108": {
        "Buffer": 19.726011991500854, 
        "Freezing": 0, 
        "QoE": 2.9428406276733643, 
        "Representation": "4", 
        "Response": 5.713599920272827, 
        "Server": "cache-01", 
        "TS": 1427430579
    }, 
    "109": {
        "Buffer": 18.723306894302368, 
        "Freezing": 0, 
        "QoE": 2.9428406276733643, 
        "Representation": "4", 
        "Response": 5.697512149810791, 
        "Server": "cache-01", 
        "TS": 1427430585
    }, 
    "110": {
        "Buffer": 18.17867112159729, 
        "Freezing": 0, 
        "QoE": 2.9428406276733643, 
        "Representation": "4", 
        "Response": 5.544559001922607, 
        "Server": "cache-01", 
        "TS": 1427430590
    }, 
    "111": {
        "Buffer": 18.314197063446045, 
        "Freezing": 0, 
        "QoE": 2.9428406276733643, 
        "Representation": "4", 
        "Response": 4.8643858432769775, 
        "Server": "cache-01", 
        "TS": 1427430595
    }, 
    "112": {
        "Buffer": 19.61630892753601, 
        "Freezing": 0, 
        "QoE": 2.9428406276733643, 
        "Representation": "4", 
        "Response": 3.697810173034668, 
        "Server": "cache-01", 
        "TS": 1427430599
    }, 
    "113": {
        "Buffer": 22.237072944641113, 
        "Freezing": 0, 
        "QoE": 2.9428406276733643, 
        "Representation": "4", 
        "Response": 2.3791580200195312, 
        "Server": "cache-01", 
        "TS": 1427430601
    }, 
    "114": {
        "Buffer": 25.435019969940186, 
        "Freezing": 0, 
        "QoE": 2.5031867016495197, 
        "Representation": "3", 
        "Response": 1.8019740581512451, 
        "Server": "cache-01", 
        "TS": 1427430603
    }, 
    "115": {
        "Buffer": 23.477783918380737, 
        "Freezing": 0, 
        "QoE": 2.5031867016495197, 
        "Representation": "3", 
        "Response": 1.8726811408996582, 
        "Server": "cache-01", 
        "TS": 1427430610
    }, 
    "116": {
        "Buffer": 27.186244010925293, 
        "Freezing": 0, 
        "QoE": 2.5031867016495197, 
        "Representation": "3", 
        "Response": 1.2914609909057617, 
        "Server": "cache-01", 
        "TS": 1427430611
    }, 
    "117": {
        "Buffer": 25.890767097473145, 
        "Freezing": 0, 
        "QoE": 1.7515933508247599, 
        "Representation": "2", 
        "Response": 1.2906928062438965, 
        "Server": "cache-01", 
        "TS": 1427430617
    }, 
    "118": {
        "Buffer": 24.348819971084595, 
        "Freezing": 0, 
        "QoE": 1.7515933508247599, 
        "Representation": "2", 
        "Response": 1.5376269817352295, 
        "Server": "cache-01", 
        "TS": 1427430624
    }, 
    "119": {
        "Buffer": 28.29882502555847, 
        "Freezing": 0, 
        "QoE": 1.7515933508247599, 
        "Representation": "2", 
        "Response": 1.0499179363250732, 
        "Server": "cache-01", 
        "TS": 1427430625
    }
}